square_skill_helpers/__init__.py
square_skill_helpers/data_api.py
square_skill_helpers/model_api.py
square_skill_helpers/model_api_deprecated.py
square_skill_helpers/square_api.py
square_skill_helpers-0.0.10.dist-info/METADATA
square_skill_helpers-0.0.10.dist-info/WHEEL
square_skill_helpers-0.0.10.dist-info/top_level.txt
square_skill_helpers-0.0.10.dist-info/RECORD
